NotificationAutomationService/__init__.py
NotificationAutomationService/__main__.py
NotificationAutomationService/api.py
NotificationAutomationService/const.py
NotificationAutomationService/service.py
pih_ntfc_auto-0.17.1.dist-info/METADATA
pih_ntfc_auto-0.17.1.dist-info/WHEEL
pih_ntfc_auto-0.17.1.dist-info/entry_points.txt
pih_ntfc_auto-0.17.1.dist-info/top_level.txt
pih_ntfc_auto-0.17.1.dist-info/RECORD
