Metadata-Version: 2.1
Name: pih-ntfc_auto
Version: 0.17.1
Summary: PIH Notification automation service package
Home-page: https://pacifichosp.com/
Author: Nikita Karachentsev
Author-email: it@pacifichosp.com
License: MIT
Requires-Dist: ipih
